termvisage/__init__.py
termvisage/__main__.py
termvisage/cli.py
termvisage/config.py
termvisage/ctlseqs.py
termvisage/exit_codes.py
termvisage/logging.py
termvisage/logging_multi.py
termvisage/notify.py
termvisage/parsers.py
termvisage/utils.py
termvisage/tui/__init__.py
termvisage/tui/keys.py
termvisage/tui/main.py
termvisage/tui/render.py
termvisage/tui/widgets.py
termvisage-0.2.0.dist-info/LICENSE
termvisage-0.2.0.dist-info/METADATA
termvisage-0.2.0.dist-info/WHEEL
termvisage-0.2.0.dist-info/entry_points.txt
termvisage-0.2.0.dist-info/top_level.txt
termvisage-0.2.0.dist-info/RECORD
