Metadata-Version: 2.1
Name: termvisage
Version: 0.2.0
Summary: Display and browse images in the terminal
Author-email: Toluwaleke Ogundipe <anonymoux47@gmail.com>
License: MIT License
Project-URL: Homepage, https://github.com/AnonymouX47/termvisage
Project-URL: Documentation, https://termvisage.readthedocs.io/
Project-URL: Source, https://github.com/AnonymouX47/termvisage
Project-URL: Repository, https://github.com/AnonymouX47/termvisage.git
Project-URL: Issues, https://github.com/AnonymouX47/termvisage/issues
Project-URL: Changelog, https://github.com/AnonymouX47/termvisage/blob/main/CHANGELOG.md
Project-URL: Funding, https://github.com/AnonymouX47/termvisage#sponsor-this-project
Keywords: image,terminal,viewer,PIL,Pillow,console,xterm,cli,tui,ANSI,ASCII-Art,kitty,iterm2,sixel,graphics
Classifier: Environment :: Console
Classifier: License :: OSI Approved :: MIT License
Classifier: Intended Audience :: End Users/Desktop
Classifier: Operating System :: POSIX :: Linux
Classifier: Operating System :: MacOS
Classifier: Operating System :: Android
Classifier: Operating System :: Microsoft :: Windows
Classifier: Programming Language :: Python :: 3
Classifier: Programming Language :: Python :: 3.8
Classifier: Programming Language :: Python :: 3.9
Classifier: Programming Language :: Python :: 3.10
Classifier: Programming Language :: Python :: 3.11
Classifier: Programming Language :: Python :: 3.12
Classifier: Programming Language :: Python :: 3 :: Only
Classifier: Topic :: Multimedia :: Graphics :: Viewers
Classifier: Topic :: Terminals :: Terminal Emulators/X Terminals
Classifier: Topic :: Utilities
Requires-Python: >=3.8
License-File: LICENSE
Requires-Dist: Pillow <11,>=10.1
Requires-Dist: term-image <0.7,>=0.6
Requires-Dist: urwid <3,>=2.1
Provides-Extra: completions
Requires-Dist: argcomplete <4,>=2 ; extra == 'completions'
